lhapdf.cpython-37m-x86_64-linux-gnu.so
a3b2bbc3ced97675ac3a71df45f55ba-6.4.0.dist-info/top_level.txt
a3b2bbc3ced97675ac3a71df45f55ba-6.4.0.dist-info/METADATA
a3b2bbc3ced97675ac3a71df45f55ba-6.4.0.dist-info/RECORD
a3b2bbc3ced97675ac3a71df45f55ba-6.4.0.dist-info/WHEEL
a3b2bbc3ced97675ac3a71df45f55ba.libs/libLHAPDF-7fed1dc4.so
