Metadata-Version: 1.0
Name: a3b2bbc3ced97675ac3a71df45f55ba
Version: 6.4.0
Summary: The LHAPDF parton density evaluation library
Home-page: https://gitlab.com/hepcedar/lhapdf/
Author: Andy Buckley
Author-email: UNKNOWN
License: UNKNOWN
Platform: UNKNOWN
